{
    "name":"",
    "description":"Nansen is a leading on-chain analytics platform founded in 2020, and is now one of the most trusted names in crypto, serving traders and institutions. Disclaimer: delegating comes with slashing risks",
    "icon":"https://raw.githubusercontent.com/nansen-ai/staking-brand-assets/main/nansen_logo.svg",
    "socials": {
       "website":"https://stake.nansen.ai",
       "github": "https://github.com/nansen-ai",
       "twitter": "https://x.com/nansen_ai",
       "telegram": "",
       "discord": ""
    }
  }